LICENSE.md
README.md
smaug/__init__.py
smaug/_itertools.py
smaug/broadcast.py
smaug/cli/__init__.py
smaug/cli/accelerator.py
smaug/cli/augment.py
smaug/cli/config.py
smaug/cli/context.py
smaug/cli/fmt.py
smaug/cli/io.py
smaug/cli/param.py
smaug/cli/processor.py
smaug/cli/transform.py
smaug/cli/validation.py
smaug/core.py
smaug/frozen.py
smaug/models/__init__.py
smaug/models/stanza.py
smaug/models/transformers.py
smaug/ops/__init__.py
smaug/ops/detection.py
smaug/ops/lang_model.py
smaug/ops/masking.py
smaug/ops/modification.py
smaug/ops/nli.py
smaug/ops/pos_tagging.py
smaug/ops/sentence.py
smaug/ops/text_generation.py
smaug/pipeline.py
smaug/promote.py
smaug/random.py
smaug/transform.py
smaug/validation.py
unbabel_smaug-0.1.3.dist-info/LICENSE.md
unbabel_smaug-0.1.3.dist-info/WHEEL
unbabel_smaug-0.1.3.dist-info/entry_points.txt
unbabel_smaug-0.1.3.dist-info/METADATA
unbabel_smaug-0.1.3.dist-info/RECORD
