Metadata-Version: 2.1
Name: unbabel-smaug
Version: 0.1.3
Summary: Sentence-level Multilingual Augmentation
Home-page: https://github.com/Unbabel/smaug
License: Apache-2.0
Keywords: Natural Language Processing,Data Augmentation
Author: Duarte Alves
Author-email: duartemalves@tecnico.ulisboa.pt
Requires-Python: >=3.8,<4.0
Classifier: Development Status :: 3 - Alpha
Classifier: Environment :: Console
Classifier: Intended Audience :: Science/Research
Classifier: License :: OSI Approved :: Apache Software License
Classifier: Programming Language :: Python :: 3
Classifier: Programming Language :: Python :: 3.8
Classifier: Programming Language :: Python :: 3.9
Classifier: Programming Language :: Python :: 3.10
Classifier: Programming Language :: Python :: 3.11
Classifier: Topic :: Scientific/Engineering :: Artificial Intelligence
Requires-Dist: PyYAML (>=6.0,<7.0)
Requires-Dist: nltk (>=3.7,<4.0)
Requires-Dist: numpy (>=1.21.4,<2.0.0)
Requires-Dist: packaging (>=21.3,<22.0)
Requires-Dist: pandas (>=1.3.4,<2.0.0)
Requires-Dist: sentencepiece (!=0.1.96)
Requires-Dist: stanza (>=1.3.0,<2.0.0)
Requires-Dist: torch (>=1.8.2,<2.0.0,!=1.13.0)
Requires-Dist: transformers (>=4.15.0,<5.0.0)
Project-URL: Repository, https://github.com/Unbabel/smaug
